setup.py
c_excel/__init__.py
c_excel/excel_dst.py
c_excel/excel_source.py
c_excel.egg-info/PKG-INFO
c_excel.egg-info/SOURCES.txt
c_excel.egg-info/dependency_links.txt
c_excel.egg-info/requires.txt
c_excel.egg-info/top_level.txt