Metadata-Version: 2.1
Name: c-excel
Version: 0.0.3
Summary: c_excel
Home-page: https://www.cnblogs.com/Evan-fanfan/p/8968093.html
Author: evanyang
Author-email: lightyiyi@qq.com
License: MIT tencent_message
Platform: UNKNOWN
